manga_down/__init__.py
manga_down/mangapanda/__init__.py
manga_down/mangapanda/chapter_list.py
manga_down/mangapanda/chapter_reader.py
manga_down/mangapanda/manga.py
manga_down/mangareader/__init__.py
manga_down/mangareader/chapter_list.py
manga_down/mangareader/chapter_reader.py
manga_down/mangareader/manga.py
manga_down-0.1.1.dist-info/LICENSE
manga_down-0.1.1.dist-info/METADATA
manga_down-0.1.1.dist-info/WHEEL
manga_down-0.1.1.dist-info/top_level.txt
manga_down-0.1.1.dist-info/RECORD
