Metadata-Version: 2.1
Name: manga-down
Version: 0.1.1
Summary: Python package to download manga available on mangareader and mangapanda
Home-page: https://github.com/shaikhsajid1111/manga-down/
Author: Shaikh Sajid
Author-email: shaikhsajid3732@gmail.com
License: UNKNOWN
Keywords: web-scraping manga-down manga-download download manga-downloader requests bs4 beautifulsoup mangreader mangapanda
Platform: UNKNOWN
Classifier: Development Status :: 4 - Beta
Classifier: Environment :: Console
Classifier: Intended Audience :: Developers
Classifier: Programming Language :: Python :: 3
Classifier: License :: OSI Approved :: MIT License
Classifier: Operating System :: Microsoft :: Windows
Classifier: Operating System :: POSIX :: Linux
Classifier: Operating System :: MacOS :: MacOS X
Requires-Python: >=3.6.9
Requires-Dist: bs4 (==0.0.1)
Requires-Dist: requests (==2.22.0)
Requires-Dist: fake-headers (==1.0.2)
